ckanext/__init__.py
ckanext/validation/__init__.py
ckanext/validation/cli.py
ckanext/validation/commands.py
ckanext/validation/common.py
ckanext/validation/controller.py
ckanext/validation/helpers.py
ckanext/validation/interfaces.py
ckanext/validation/jobs.py
ckanext/validation/model.py
ckanext/validation/plugin.py
ckanext/validation/presets.json
ckanext/validation/settings.py
ckanext/validation/utils.py
ckanext/validation/validators.py
ckanext/validation/views.py
ckanext/validation/examples/__init__.py
ckanext/validation/examples/ckan_default_schema.json
ckanext/validation/logic/__init__.py
ckanext/validation/logic/action.py
ckanext/validation/logic/auth.py
ckanext/validation/templates/package/resource_read.html
ckanext/validation/templates/package/snippets/resource_item.html
ckanext/validation/templates/scheming/form_snippets/hidden.html
ckanext/validation/templates/scheming/form_snippets/resource_schema.html
ckanext/validation/templates/scheming/form_snippets/validation_options.html
ckanext/validation/templates/scheming/snippets/errors.html
ckanext/validation/templates/validation/validation_read.html
ckanext/validation/templates/validation/snippets/validation_report_asset.html
ckanext/validation/templates/validation/snippets/validation_report_dialog.html
ckanext/validation/templates/validation/snippets/validation_report_dialog_bs2.html
ckanext/validation/tests/__init__.py
ckanext/validation/tests/fixtures.py
ckanext/validation/tests/helpers.py
ckanext/validation/tests/test_form.py
ckanext/validation/tests/test_helpers.py
ckanext/validation/tests/test_interfaces.py
ckanext/validation/tests/test_jobs.py
ckanext/validation/tests/test_logic.py
ckanext/validation/tests/test_plugin.py
ckanext/validation/tests/test_utils.py
ckanext/validation/tests/test_validators.py
ckanext/validation/webassets/resource.config
ckanext/validation/webassets/webassets.yml
ckanext/validation/webassets/css/validation-report-form.css
ckanext/validation/webassets/css/validation-report.css
ckanext_validation-2.2.0.dist-info/LICENSE
ckanext_validation-2.2.0.dist-info/METADATA
ckanext_validation-2.2.0.dist-info/WHEEL
ckanext_validation-2.2.0.dist-info/entry_points.txt
ckanext_validation-2.2.0.dist-info/top_level.txt
ckanext_validation-2.2.0.dist-info/RECORD
