Metadata-Version: 2.1
Name: ckanext-validation
Version: 2.2.0
Summary: Data description and validation for CKAN with Frictionless Data tools.
Author: Edgar Z. Alvarenga (aivuk)
Author-email: Open Knowledge Foundation <info@okfn.org>, "Adrià Mercader (amercader)" <amercadero@gmail.com>, "Jesse Vickery (JVickery-TBS)" <jesse.vickery@tbs-sct.gc.ca>, ThrawnCA <carl.antuar@smartservice.qld.gov.au>, "William Dutton (duttonw)" <william.dutton@qld.gov.au>
Maintainer-email: Open Knowledge Foundation <info@okfn.org>, "Adrià Mercader (amercader)" <amercadero@gmail.com>, "William Dutton (duttonw)" <william.dutton@qld.gov.au>, ThrawnCA <carl.antuar@smartservice.qld.gov.au>
License: AGPL
Project-URL: Homepage, https://github.com/ckan/ckanext-validation
Keywords: CKAN,extension,validation
Classifier: Development Status :: 5 - Production/Stable
Classifier: License :: OSI Approved :: GNU Affero General Public License v3 or later (AGPLv3+)
Classifier: Programming Language :: Python :: 3.7
Classifier: Programming Language :: Python :: 3.8
Classifier: Programming Language :: Python :: 3.9
Classifier: Programming Language :: Python :: 3.10
License-File: LICENSE
Requires-Dist: typing_extensions
Provides-Extra: test
Requires-Dist: pytest-factoryboy; extra == "test"
